sendx_python_sdk/__init__.py
sendx_python_sdk/api_client.py
sendx_python_sdk/api_response.py
sendx_python_sdk/configuration.py
sendx_python_sdk/exceptions.py
sendx_python_sdk/py.typed
sendx_python_sdk/rest.py
sendx_python_sdk/api/__init__.py
sendx_python_sdk/api/campaign_api.py
sendx_python_sdk/api/contact_api.py
sendx_python_sdk/api/custom_field_api.py
sendx_python_sdk/api/email_sending_api.py
sendx_python_sdk/api/event_api.py
sendx_python_sdk/api/events_api.py
sendx_python_sdk/api/getting_started_api.py
sendx_python_sdk/api/list_api.py
sendx_python_sdk/api/post_api.py
sendx_python_sdk/api/post_category_api.py
sendx_python_sdk/api/post_tag_api.py
sendx_python_sdk/api/report_api.py
sendx_python_sdk/api/reports_api.py
sendx_python_sdk/api/sender_api.py
sendx_python_sdk/api/tag_api.py
sendx_python_sdk/api/tags_api.py
sendx_python_sdk/api/team_member_api.py
sendx_python_sdk/api/template_api.py
sendx_python_sdk/api/tracking_api.py
sendx_python_sdk/api/webhook_api.py
sendx_python_sdk/models/__init__.py
sendx_python_sdk/models/campaign.py
sendx_python_sdk/models/campaign_dashboard_data.py
sendx_python_sdk/models/campaign_request.py
sendx_python_sdk/models/contact.py
sendx_python_sdk/models/contact_request.py
sendx_python_sdk/models/create_response.py
sendx_python_sdk/models/custom_event_request.py
sendx_python_sdk/models/custom_field.py
sendx_python_sdk/models/customfield_customfield_id_delete200_response.py
sendx_python_sdk/models/dashboard_stats.py
sendx_python_sdk/models/delete_campaign200_response.py
sendx_python_sdk/models/delete_request.py
sendx_python_sdk/models/delete_response.py
sendx_python_sdk/models/e_custom_field.py
sendx_python_sdk/models/error_response.py
sendx_python_sdk/models/event_response.py
sendx_python_sdk/models/events_revenue_postback_get200_response.py
sendx_python_sdk/models/events_revenue_postback_get400_response.py
sendx_python_sdk/models/events_revenue_postback_get500_response.py
sendx_python_sdk/models/identify_request.py
sendx-2.0.0.dist-info/METADATA
sendx-2.0.0.dist-info/WHEEL
sendx-2.0.0.dist-info/top_level.txt
sendx-2.0.0.dist-info/RECORD
