Metadata-Version: 2.4
Name: SendX
Version: 2.0.0
Summary: SendX REST API
Home-page: 
Author: SendX Dev Team
Author-email: support@sendx.io
Keywords: SendX,email marketing,SendX REST API,email,marketing
Requires-Dist: urllib3<2.1.0,>=1.25.3
Requires-Dist: python-dateutil
Requires-Dist: pydantic>=2
Requires-Dist: typing-extensions>=4.7.1
Dynamic: author
Dynamic: author-email
Dynamic: description
Dynamic: description-content-type
Dynamic: keywords
Dynamic: requires-dist
Dynamic: summary
